rencom/__init__.py
rencom/_http.py
rencom/auth.py
rencom/client.py
rencom/exceptions.py
rencom/py.typed
rencom/x402.py
rencom/_generated/README.md
rencom/_generated/__init__.py
rencom/_generated/models.py
rencom/ucp/__init__.py
rencom/ucp/analytics.py
rencom/ucp/merchants.py
rencom/ucp/products.py
rencom-0.1.4.dist-info/METADATA
rencom-0.1.4.dist-info/WHEEL
rencom-0.1.4.dist-info/licenses/LICENSE
rencom-0.1.4.dist-info/RECORD
